src/__init__.py
src/cli.py
src/log.py
src/starter.py
multi_start-1.2.0.dist-info/LICENSE
multi_start-1.2.0.dist-info/METADATA
multi_start-1.2.0.dist-info/WHEEL
multi_start-1.2.0.dist-info/entry_points.txt
multi_start-1.2.0.dist-info/RECORD
