Metadata-Version: 2.1
Name: multi-start
Version: 1.2.0
Summary: Run multiple services inside a docker container
Home-page: https://github.com/ioxiocom/multi-start
License: BSD-3-Clause
Author: IOXIO Ltd
Requires-Python: >=3.10,<4.0
Classifier: License :: OSI Approved :: BSD License
Classifier: Programming Language :: Python :: 3
Classifier: Programming Language :: Python :: 3.10
Classifier: Programming Language :: Python :: 3.11
Classifier: Programming Language :: Python :: 3.12
Classifier: Programming Language :: Python :: 3.13
Requires-Dist: httpx (>=0.24.1,<0.25.0)
Requires-Dist: typer (>=0.9.0,<0.10.0)
Project-URL: Repository, https://github.com/ioxiocom/multi-start
